torchflame
