Metadata-Version: 1.2
Name: torchflame
Version: 0.1.20201204.1
Summary: a small extension package of pytorch
Home-page: UNKNOWN
Author: Jewelry
Author-email: 3180105772@zju.edu.cn
License: MIT
Platform: UNKNOWN
Requires-Python: >=3.6
